hived_rpc_scanner
