Metadata-Version: 1.0
Name: hived-rpc-scanner
Version: 0.0.2
Summary: A tool to check status of certain endpoints on Hived RPC
Home-page: https://github.com/emre/hived-rpc-scanner
Author: emre yilmaz
Author-email: mail@emreyilmaz.me
License: MIT
Platform: UNKNOWN
